mapstep/__init__.py
mapstep/mapstep.py
mapstep/static/index.html
mapstep/static/css/style.css
mapstep/static/img/marker-icon-green.png
mapstep/static/img/marker-icon-red.png
mapstep/static/img/marker-icon-yellow.png
mapstep/static/img/marker-shadow.png
mapstep/static/js/app.js
mapstep-1.0.0.dist-info/DESCRIPTION.rst
mapstep-1.0.0.dist-info/METADATA
mapstep-1.0.0.dist-info/RECORD
mapstep-1.0.0.dist-info/WHEEL
mapstep-1.0.0.dist-info/entry_points.txt
mapstep-1.0.0.dist-info/metadata.json
mapstep-1.0.0.dist-info/top_level.txt
